local_qwen3b_part035/__init__.py
local_qwen3b_part035/qwen2.5-3b-instruct-q5_k_m.gguf.part_035
local_qwen3b_part035-0.0.1.dist-info/METADATA
local_qwen3b_part035-0.0.1.dist-info/WHEEL
local_qwen3b_part035-0.0.1.dist-info/top_level.txt
local_qwen3b_part035-0.0.1.dist-info/RECORD
